<?xml version="1.0" encoding="UTF-8"?>
<!DOCTYPE plist PUBLIC "-//Apple//DTD PLIST 1.0//EN" "http://www.apple.com/DTDs/PropertyList-1.0.dtd"/>

<plist version="1.0">
    <dict>
        <key>ROOT</key>
        <array>
            <dict>
                <key>id</key>
                <string>217</string>
                <key>Emitters</key>
                <dict>
                    <key>emitters</key>
                    <array>
                        <string>221</string>
                    </array>
                </dict>
            </dict>
            <dict>
                <key>id</key>
                <string>231</string>
                <key>Emitters</key>
                <dict>
                    <key>emitters</key>
                    <array>
                        <string>233</string>
                    </array>
                </dict>
            </dict>
            <dict>
                <key>id</key>
                <string>584</string>
                <key>Emitters</key>
                <dict>
                    <key>emitters</key>
                    <array>
                        <string>586</string>
                    </array>
                </dict>
            </dict>
            <dict>
                <key>id</key>
                <string>945</string>
                <key>Emitters</key>
                <dict>
                    <key>emitters</key>
                    <array>
                        <string>947</string>
                    </array>
                </dict>
            </dict>
            <dict>
                <key>id</key>
                <string>951</string>
                <key>Emitters</key>
                <dict>
                    <key>emitters</key>
                    <array>
                        <string>953</string>
                        <string>956</string>
                    </array>
                </dict>
            </dict>
            <dict>
                <key>id</key>
                <string>984</string>
                <key>Emitters</key>
                <dict>
                    <key>emitters</key>
                    <array>
                        <string>990</string>
                    </array>
                </dict>
            </dict>
            <dict>
                <key>id</key>
                <string>1047</string>
                <key>Emitters</key>
                <dict>
                    <key>emitters</key>
                    <array>
                        <string>1049</string>
                    </array>
                </dict>
            </dict>
            <dict>
                <key>id</key>
                <string>1251</string>
                <key>Emitters</key>
                <dict>
                    <key>emitters</key>
                    <array>
                        <string>1253</string>
                    </array>
                </dict>
            </dict>
            <dict>
                <key>id</key>
                <string>1317</string>
                <key>Emitters</key>
                <dict>
                    <key>emitters</key>
                    <array>
                        <string>1319</string>
                        <string>1320</string>
                    </array>
                </dict>
            </dict>
            <dict>
                <key>id</key>
                <string>3215</string>
                <key>Emitters</key>
                <dict>
                    <key>emitters</key>
                    <array>
                        <string>3217</string>
                    </array>
                </dict>
            </dict>
            <dict>
                <key>id</key>
                <string>3235</string>
                <key>Emitters</key>
                <dict>
                    <key>emitters</key>
                    <array>
                        <string>3237</string>
                    </array>
                </dict>
            </dict>
            <dict>
                <key>id</key>
                <string>3241</string>
                <key>Emitters</key>
                <dict>
                    <key>emitters</key>
                    <array>
                        <string>3243</string>
                    </array>
                </dict>
            </dict>
            <dict>
                <key>id</key>
                <string>3247</string>
                <key>Emitters</key>
                <dict>
                    <key>emitters</key>
                    <array>
                        <string>3249</string>
                    </array>
                </dict>
            </dict>
            <dict>
                <key>id</key>
                <string>3253</string>
                <key>Emitters</key>
                <dict>
                    <key>emitters</key>
                    <array>
                        <string>3255</string>
                    </array>
                </dict>
            </dict>
            <dict>
                <key>id</key>
                <string>3259</string>
                <key>Emitters</key>
                <dict>
                    <key>emitters</key>
                    <array>
                        <string>3261</string>
                    </array>
                </dict>
            </dict>
            <dict>
                <key>id</key>
                <string>3265</string>
                <key>Emitters</key>
                <dict>
                    <key>emitters</key>
                    <array>
                        <string>3267</string>
                    </array>
                </dict>
            </dict>
            <dict>
                <key>id</key>
                <string>3271</string>
                <key>Emitters</key>
                <dict>
                    <key>emitters</key>
                    <array>
                        <string>3273</string>
                    </array>
                </dict>
            </dict>
            <dict>
                <key>id</key>
                <string>3277</string>
                <key>Emitters</key>
                <dict>
                    <key>emitters</key>
                    <array>
                        <string>3279</string>
                    </array>
                </dict>
            </dict>
            <dict>
                <key>id</key>
                <string>3283</string>
                <key>Emitters</key>
                <dict>
                    <key>emitters</key>
                    <array>
                        <string>3285</string>
                    </array>
                </dict>
            </dict>
            <dict>
                <key>id</key>
                <string>3289</string>
                <key>Emitters</key>
                <dict>
                    <key>emitters</key>
                    <array>
                        <string>3291</string>
                    </array>
                </dict>
            </dict>
            <dict>
                <key>id</key>
                <string>3295</string>
                <key>Emitters</key>
                <dict>
                    <key>emitters</key>
                    <array>
                        <string>3297</string>
                    </array>
                </dict>
            </dict>
            <dict>
                <key>id</key>
                <string>3301</string>
                <key>Emitters</key>
                <dict>
                    <key>emitters</key>
                    <array>
                        <string>3303</string>
                    </array>
                </dict>
            </dict>
            <dict>
                <key>id</key>
                <string>3307</string>
                <key>Emitters</key>
                <dict>
                    <key>emitters</key>
                    <array>
                        <string>3309</string>
                    </array>
                </dict>
            </dict>
            <dict>
                <key>id</key>
                <string>3313</string>
                <key>Emitters</key>
                <dict>
                    <key>emitters</key>
                    <array>
                        <string>3315</string>
                    </array>
                </dict>
            </dict>
            <dict>
                <key>id</key>
                <string>3319</string>
                <key>Emitters</key>
                <dict>
                    <key>emitters</key>
                    <array>
                        <string>3321</string>
                    </array>
                </dict>
            </dict>
            <dict>
                <key>id</key>
                <string>3325</string>
                <key>Emitters</key>
                <dict>
                    <key>emitters</key>
                    <array>
                        <string>3327</string>
                    </array>
                </dict>
            </dict>
            <dict>
                <key>id</key>
                <string>4628</string>
                <key>Emitters</key>
                <dict>
                    <key>emitters</key>
                    <array>
                        <string>4630</string>
                    </array>
                </dict>
            </dict>
            <dict>
                <key>id</key>
                <string>4640</string>
                <key>Emitters</key>
                <dict>
                    <key>emitters</key>
                    <array>
                        <string>4642</string>
                    </array>
                </dict>
            </dict>
            <dict>
                <key>id</key>
                <string>4646</string>
                <key>Emitters</key>
                <dict>
                    <key>emitters</key>
                    <array>
                        <string>4648</string>
                    </array>
                </dict>
            </dict>
            <dict>
                <key>id</key>
                <string>4652</string>
                <key>Emitters</key>
                <dict>
                    <key>emitters</key>
                    <array>
                        <string>4654</string>
                    </array>
                </dict>
            </dict>
            <dict>
                <key>id</key>
                <string>4658</string>
                <key>Emitters</key>
                <dict>
                    <key>emitters</key>
                    <array>
                        <string>4660</string>
                    </array>
                </dict>
            </dict>
            <dict>
                <key>id</key>
                <string>4664</string>
                <key>Emitters</key>
                <dict>
                    <key>emitters</key>
                    <array>
                        <string>4666</string>
                    </array>
                </dict>
            </dict>
            <dict>
                <key>id</key>
                <string>4670</string>
                <key>Emitters</key>
                <dict>
                    <key>emitters</key>
                    <array>
                        <string>4672</string>
                    </array>
                </dict>
            </dict>
            <dict>
                <key>id</key>
                <string>4676</string>
                <key>Emitters</key>
                <dict>
                    <key>emitters</key>
                    <array>
                        <string>4678</string>
                    </array>
                </dict>
            </dict>
            <dict>
                <key>id</key>
                <string>4682</string>
                <key>Emitters</key>
                <dict>
                    <key>emitters</key>
                    <array>
                        <string>4684</string>
                    </array>
                </dict>
            </dict>
            <dict>
                <key>id</key>
                <string>4688</string>
                <key>Emitters</key>
                <dict>
                    <key>emitters</key>
                    <array>
                        <string>4690</string>
                    </array>
                </dict>
            </dict>
            <dict>
                <key>id</key>
                <string>4694</string>
                <key>Emitters</key>
                <dict>
                    <key>emitters</key>
                    <array>
                        <string>4696</string>
                    </array>
                </dict>
            </dict>
            <dict>
                <key>id</key>
                <string>4700</string>
                <key>Emitters</key>
                <dict>
                    <key>emitters</key>
                    <array>
                        <string>4702</string>
                    </array>
                </dict>
            </dict>
            <dict>
                <key>id</key>
                <string>4706</string>
                <key>Emitters</key>
                <dict>
                    <key>emitters</key>
                    <array>
                        <string>4708</string>
                    </array>
                </dict>
            </dict>
            <dict>
                <key>id</key>
                <string>4712</string>
                <key>Emitters</key>
                <dict>
                    <key>emitters</key>
                    <array>
                        <string>4714</string>
                    </array>
                </dict>
            </dict>
            <dict>
                <key>id</key>
                <string>4718</string>
                <key>Emitters</key>
                <dict>
                    <key>emitters</key>
                    <array>
                        <string>4720</string>
                    </array>
                </dict>
            </dict>
            <dict>
                <key>id</key>
                <string>4724</string>
                <key>Emitters</key>
                <dict>
                    <key>emitters</key>
                    <array>
                        <string>4726</string>
                    </array>
                </dict>
            </dict>
        </array>
    </dict>
</plist>
